minq/__init__.py
minq-0.0.1.dist-info/LICENSE
minq-0.0.1.dist-info/METADATA
minq-0.0.1.dist-info/WHEEL
minq-0.0.1.dist-info/top_level.txt
minq-0.0.1.dist-info/RECORD
