Metadata-Version: 2.1
Name: minq
Version: 0.0.1
Summary: Tiny quantum gate library based on NumPy
License: MIT License
Project-URL: Homepage, https://github.com/fwcd/minq
Project-URL: Repository, https://github.com/fwcd/minq
Keywords: quantum,computing,circuit,gate,numpy
Classifier: Topic :: Scientific/Engineering :: Mathematics
Requires-Python: >=3.9
License-File: LICENSE
Requires-Dist: numpy <2,>=1.26
